espressodb/__init__.py
espressodb/manage.py
espressodb/base/__init__.py
espressodb/base/admin.py
espressodb/base/apps.py
espressodb/base/exceptions.py
espressodb/base/forms.py
espressodb/base/models.py
espressodb/base/signals.py
espressodb/base/urls.py
espressodb/base/views.py
espressodb/base/static/__init__.py
espressodb/base/static/logo.svg
espressodb/base/static/__pycache__/__init__.cpython-38.pyc
espressodb/base/static/admin/extra.css
espressodb/base/static/css/base.css
espressodb/base/static/css/fa-all.min.css
espressodb/base/static/css/katex.min.css
espressodb/base/static/css/prettify.css
espressodb/base/static/icons/android-chrome-192x192.png
espressodb/base/static/icons/android-chrome-384x384.png
espressodb/base/static/icons/apple-touch-icon.png
espressodb/base/static/icons/browserconfig.xml
espressodb/base/static/icons/favicon-16x16.png
espressodb/base/static/icons/favicon-32x32.png
espressodb/base/static/icons/favicon.ico
espressodb/base/static/icons/mstile-150x150.png
espressodb/base/static/icons/safari-pinned-tab.svg
espressodb/base/static/js/katex-auto-render.min.js
espressodb/base/static/js/katex.min.js
espressodb/base/static/js/prettify.js
espressodb/base/static/webfonts/fa-brands-400.eot
espressodb/base/static/webfonts/fa-brands-400.svg
espressodb/base/static/webfonts/fa-brands-400.ttf
espressodb/base/static/webfonts/fa-brands-400.woff
espressodb/base/static/webfonts/fa-brands-400.woff2
espressodb/base/static/webfonts/fa-regular-400.eot
espressodb/base/static/webfonts/fa-regular-400.svg
espressodb/base/static/webfonts/fa-regular-400.ttf
espressodb/base/static/webfonts/fa-regular-400.woff
espressodb/base/static/webfonts/fa-regular-400.woff2
espressodb/base/static/webfonts/fa-solid-900.eot
espressodb/base/static/webfonts/fa-solid-900.svg
espressodb/base/static/webfonts/fa-solid-900.ttf
espressodb/base/static/webfonts/fa-solid-900.woff
espressodb/base/static/webfonts/fa-solid-900.woff2
espressodb/base/templates/base.html
espressodb-1.2.1.dist-info/LICENSE.md
espressodb-1.2.1.dist-info/METADATA
espressodb-1.2.1.dist-info/WHEEL
espressodb-1.2.1.dist-info/entry_points.txt
espressodb-1.2.1.dist-info/top_level.txt
espressodb-1.2.1.dist-info/RECORD
