Metadata-Version: 2.1
Name: espressodb
Version: 1.2.1
Summary: Science database interface using Django as the content manager.
Home-page: https://github.com/callat-qcd/espressodb
Author: @cchang5, @ckoerber
Author-email: ckoerber@berkeley.edu
License: UNKNOWN
Project-URL: Bug Reports, https://github.com/callat-qcd/espressodb/issues
Project-URL: Source, https://github.com/callat-qcd/espressodb
Project-URL: Documentation, https://espressodb.readthedocs.io
Keywords: Database,Workflow,Django
Platform: UNKNOWN
Classifier: Development Status :: 5 - Production/Stable
Classifier: Intended Audience :: Science/Research
Classifier: Topic :: Database :: Database Engines/Servers
Classifier: Topic :: Database
Classifier: Topic :: Scientific/Engineering
Classifier: Intended Audience :: Science/Research
Classifier: Intended Audience :: Developers
Classifier: Operating System :: OS Independent
Classifier: Framework :: Django :: 2.2
Classifier: Framework :: Django :: 3.0
Classifier: Programming Language :: Python :: 3.6
Classifier: Programming Language :: Python :: 3.7
Classifier: License :: OSI Approved :: BSD License
Requires-Python: >=3.6
Requires-Dist: Django (>=2.2.2)
Requires-Dist: django-extensions (>=2.2.1)
Requires-Dist: django-bootstrap4 (>=0.0.6)
Requires-Dist: django-widget-tweaks (>=1.4.5)
Requires-Dist: django-pandas (>=0.6.1)
Requires-Dist: PyYAML (>=3.13)
Provides-Extra: dev
Requires-Dist: sphinx (>=2.2.0) ; extra == 'dev'
Requires-Dist: recommonmark (>=0.6.0) ; extra == 'dev'
Requires-Dist: sphinx-rtd-theme (>=0.4.3) ; extra == 'dev'
Requires-Dist: sphinx-autodoc-typehints (>=1.8.0) ; extra == 'dev'
Requires-Dist: sphinx-markdown-tables (>=0.0.9) ; extra == 'dev'
Requires-Dist: beautifulsoup4 (>=4.8.1) ; extra == 'dev'
Requires-Dist: pytest (>=4.5.0) ; extra == 'dev'
Requires-Dist: pytest-django (>=3.6.0) ; extra == 'dev'
Requires-Dist: pytest-env (>=0.6.2) ; extra == 'dev'
